{
  "repo": "OldSaltFish-vscode-extension-downloader",
  "events": [
    {
      "t": 0,
      "patterns": [
        "other"
      ],
      "astFeatures": {
        "functions": 0,
        "classes": 0,
        "dependencies": 0,
        "calls": 0,
        "untested": 0
      },
      "commit": "9be07a12c4b4481a9ebb1a3353c575657666b6e7",
      "timestamp": "2025-06-09T00:37:19+08:00"
    },
    {
      "t": 1,
      "patterns": [
        "other"
      ],
      "astFeatures": {
        "functions": 0,
        "classes": 0,
        "dependencies": 0,
        "calls": 0,
        "untested": 0
      },
      "commit": "cc83d17d3b59c2f09f34fa9785d75457617eb0d2",
      "timestamp": "2025-06-09T00:37:49+08:00"
    },
    {
      "t": 2,
      "patterns": [
        "other"
      ],
      "astFeatures": {
        "functions": 0,
        "classes": 0,
        "dependencies": 0,
        "calls": 0,
        "untested": 0
      },
      "commit": "7d712e9a7abeeab040d0a7569433534fe177f59a",
      "timestamp": "2025-06-09T13:00:26+08:00"
    },
    {
      "t": 3,
      "patterns": [
        "documentation"
      ],
      "astFeatures": {
        "functions": 0,
        "classes": 0,
        "dependencies": 0,
        "calls": 0,
        "untested": 0
      },
      "commit": "3642c207374b1660d5750f3b35940af16c2086a2",
      "timestamp": "2025-06-09T13:45:43+08:00"
    },
    {
      "t": 4,
      "patterns": [
        "other"
      ],
      "astFeatures": {
        "functions": 0,
        "classes": 0,
        "dependencies": 0,
        "calls": 0,
        "untested": 0
      },
      "commit": "8e91ee33349095e07546f9625605e51278910610",
      "timestamp": "2025-06-09T22:30:10+08:00"
    },
    {
      "t": 5,
      "patterns": [
        "other"
      ],
      "astFeatures": {
        "functions": 0,
        "classes": 0,
        "dependencies": 0,
        "calls": 0,
        "untested": 0
      },
      "commit": "60ddc408db5b5174416d27e88d003dbb9ce53800",
      "timestamp": "2025-06-10T00:57:24+08:00"
    },
    {
      "t": 6,
      "patterns": [
        "documentation"
      ],
      "astFeatures": {
        "functions": 0,
        "classes": 0,
        "dependencies": 0,
        "calls": 0,
        "untested": 0
      },
      "commit": "3444ab7b8269993eb3974ec2bd12ff646f9472e8",
      "timestamp": "2025-06-10T01:02:18+08:00"
    },
    {
      "t": 7,
      "patterns": [
        "other"
      ],
      "astFeatures": {
        "functions": 0,
        "classes": 0,
        "dependencies": 0,
        "calls": 0,
        "untested": 0
      },
      "commit": "0ca8c274423367915cb2e01f69977bbf1b9f0d3a",
      "timestamp": "2025-06-10T01:11:45+08:00"
    },
    {
      "t": 8,
      "patterns": [
        "other"
      ],
      "astFeatures": {
        "functions": 0,
        "classes": 0,
        "dependencies": 0,
        "calls": 0,
        "untested": 0
      },
      "commit": "220e1240564b16bcbb247d156bbed9a69be79263",
      "timestamp": "2025-07-04T10:18:16+08:00"
    },
    {
      "t": 9,
      "patterns": [
        "other"
      ],
      "astFeatures": {
        "functions": 0,
        "classes": 0,
        "dependencies": 0,
        "calls": 0,
        "untested": 0
      },
      "commit": "317a6e4f2c10c3717c93c0b7850aa4d86c42d7b7",
      "timestamp": "2025-08-12T03:51:48+08:00"
    },
    {
      "t": 10,
      "patterns": [
        "other"
      ],
      "astFeatures": {
        "functions": 0,
        "classes": 0,
        "dependencies": 0,
        "calls": 0,
        "untested": 0
      },
      "commit": "b73c1e5a679535c9bb7a5f98dd0c3e51ef76995e",
      "timestamp": "2025-09-03T00:52:07+08:00"
    },
    {
      "t": 11,
      "patterns": [
        "other"
      ],
      "astFeatures": {
        "functions": 0,
        "classes": 0,
        "dependencies": 0,
        "calls": 0,
        "untested": 0
      },
      "commit": "8940fe7f7c35c0e928464d90cb79ada2a169c44a",
      "timestamp": "2025-10-13T23:33:40+08:00"
    },
    {
      "t": 12,
      "patterns": [
        "other"
      ],
      "astFeatures": {
        "functions": 0,
        "classes": 0,
        "dependencies": 0,
        "calls": 0,
        "untested": 0
      },
      "commit": "2a51f4e60f4858e86f3b745a5474ae064fb83b69",
      "timestamp": "2025-10-14T14:08:39+08:00"
    },
    {
      "t": 13,
      "patterns": [
        "documentation"
      ],
      "astFeatures": {
        "functions": 0,
        "classes": 0,
        "dependencies": 0,
        "calls": 0,
        "untested": 0
      },
      "commit": "6ab392e736c5b83ccf109cff071bcfdc1a44f3e6",
      "timestamp": "2025-10-14T14:17:42+08:00"
    },
    {
      "t": 14,
      "patterns": [
        "other"
      ],
      "astFeatures": {
        "functions": 0,
        "classes": 0,
        "dependencies": 0,
        "calls": 0,
        "untested": 0
      },
      "commit": "c815d3b3220506b371a7b0ba94cffbac119e88b2",
      "timestamp": "2025-10-14T17:52:55+08:00"
    },
    {
      "t": 15,
      "patterns": [
        "other"
      ],
      "astFeatures": {
        "functions": 0,
        "classes": 0,
        "dependencies": 0,
        "calls": 0,
        "untested": 0
      },
      "commit": "2721ae55d6d077e2f84dc5c72b2cd3b6c842faf3",
      "timestamp": "2025-10-14T22:05:22+08:00"
    }
  ],
  "totalCommits": 16,
  "duration_ms": 0
}